{
  "lokasi": {
    "adm1": "35",
    "adm2": "35.07",
    "adm3": "35.07.03",
    "adm4": "35.07.03.2001",
    "provinsi": "Jawa Timur",
    "kotkab": "Malang",
    "kecamatan": "Bantur",
    "desa": "Wonokerto",
    "lon": 112.5937143111,
    "lat": -8.2407345095,
    "timezone": "Asia/Jakarta"
  },
  "data": [
    {
      "lokasi": {
        "adm1": "35",
        "adm2": "35.07",
        "adm3": "35.07.03",
        "adm4": "35.07.03.2001",
        "provinsi": "Jawa Timur",
        "kotkab": "Malang",
        "kecamatan": "Bantur",
        "desa": "Wonokerto",
        "lon": 112.5937143111,
        "lat": -8.2407345095,
        "timezone": "+0700",
        "type": "adm4"
      },
      "cuaca": [
        [
          {
            "datetime": "2026-06-24T03:00:00Z",
            "t": 29,
            "tcc": 96,
            "tp": 0.2,
            "weather": 3,
            "weather_desc": "Berawan",
            "weather_desc_en": "Mostly Cloudy",
            "wd_deg": 127,
            "wd": "E",
            "wd_to": "W",
            "ws": 12.4,
            "hu": 62,
            "vs": 18040,
            "vs_text": "> 10 km",
            "time_index": "2-3",
            "analysis_date": "2026-06-24T00:00:00",
            "image": "https://api-apps.bmkg.go.id/storage/icon/cuaca/berawan-am.svg",
            "utc_datetime": "2026-06-24 03:00:00",
            "local_datetime": "2026-06-24 10:00:00"
          },
          {
            "datetime": "2026-06-24T06:00:00Z",
            "t": 28,
            "tcc": 96,
            "tp": 0.2,
            "weather": 3,
            "weather_desc": "Berawan",
            "weather_desc_en": "Mostly Cloudy",
            "wd_deg": 132,
            "wd": "E",
            "wd_to": "W",
            "ws": 23.2,
            "hu": 68,
            "vs": 16629,
            "vs_text": "> 10 km",
            "time_index": "5-6",
            "analysis_date": "2026-06-24T00:00:00",
            "image": "https://api-apps.bmkg.go.id/storage/icon/cuaca/berawan-am.svg",
            "utc_datetime": "2026-06-24 06:00:00",
            "local_datetime": "2026-06-24 13:00:00"
          },
          {
            "datetime": "2026-06-24T09:00:00Z",
            "t": 24,
            "tcc": 74,
            "tp": 0,
            "weather": 2,
            "weather_desc": "Cerah Berawan",
            "weather_desc_en": "Partly Cloudy",
            "wd_deg": 126,
            "wd": "E",
            "wd_to": "W",
            "ws": 16.2,
            "hu": 86,
            "vs": 17087,
            "vs_text": "> 10 km",
            "time_index": "8-9",
            "analysis_date": "2026-06-24T00:00:00",
            "image": "https://api-apps.bmkg.go.id/storage/icon/cuaca/cerah berawan-am.svg",
            "utc_datetime": "2026-06-24 09:00:00",
            "local_datetime": "2026-06-24 16:00:00"
          },
          {
            "datetime": "2026-06-24T12:00:00Z",
            "t": 23,
            "tcc": 83,
            "tp": 0,
            "weather": 2,
            "weather_desc": "Cerah Berawan",
            "weather_desc_en": "Partly Cloudy",
            "wd_deg": 119,
            "wd": "E",
            "wd_to": "W",
            "ws": 11.6,
            "hu": 92,
            "vs": 18616,
            "vs_text": "> 10 km",
            "time_index": "11-12",
            "analysis_date": "2026-06-24T00:00:00",
            "image": "https://api-apps.bmkg.go.id/storage/icon/cuaca/cerah berawan-pm.svg",
            "utc_datetime": "2026-06-24 12:00:00",
            "local_datetime": "2026-06-24 19:00:00"
          },
          {
            "datetime": "2026-06-24T15:00:00Z",
            "t": 22,
            "tcc": 61,
            "tp": 0,
            "weather": 2,
            "weather_desc": "Cerah Berawan",
            "weather_desc_en": "Partly Cloudy",
            "wd_deg": 113,
            "wd": "E",
            "wd_to": "W",
            "ws": 10.1,
            "hu": 97,
            "vs": 14548,
            "vs_text": "> 10 km",
            "time_index": "14-15",
            "analysis_date": "2026-06-24T00:00:00",
            "image": "https://api-apps.bmkg.go.id/storage/icon/cuaca/cerah berawan-pm.svg",
            "utc_datetime": "2026-06-24 15:00:00",
            "local_datetime": "2026-06-24 22:00:00"
          }
        ],
        [
          {
            "datetime": "2026-06-24T18:00:00Z",
            "t": 22,
            "tcc": 38,
            "tp": 0,
            "weather": 1,
            "weather_desc": "Cerah",
            "weather_desc_en": "Sunny",
            "wd_deg": 99,
            "wd": "E",
            "wd_to": "W",
            "ws": 9.6,
            "hu": 95,
            "vs": 13430,
            "vs_text": "> 10 km",
            "time_index": "17-18",
            "analysis_date": "2026-06-24T00:00:00",
            "image": "https://api-apps.bmkg.go.id/storage/icon/cuaca/cerah-pm.svg",
            "utc_datetime": "2026-06-24 18:00:00",
            "local_datetime": "2026-06-25 01:00:00"
          },
          {
            "datetime": "2026-06-24T21:00:00Z",
            "t": 21,
            "tcc": 5,
            "tp": 0,
            "weather": 0,
            "weather_desc": "Cerah",
            "weather_desc_en": "Sunny",
            "wd_deg": 90,
            "wd": "E",
            "wd_to": "W",
            "ws": 7.9,
            "hu": 94,
            "vs": 11769,
            "vs_text": "> 10 km",
            "time_index": "20-21",
            "analysis_date": "2026-06-24T00:00:00",
            "image": "https://api-apps.bmkg.go.id/storage/icon/cuaca/cerah-pm.svg",
            "utc_datetime": "2026-06-24 21:00:00",
            "local_datetime": "2026-06-25 04:00:00"
          },
          {
            "datetime": "2026-06-25T00:00:00Z",
            "t": 25,
            "tcc": 2,
            "tp": 0,
            "weather": 0,
            "weather_desc": "Cerah",
            "weather_desc_en": "Sunny",
            "wd_deg": 108,
            "wd": "E",
            "wd_to": "W",
            "ws": 13.1,
            "hu": 76,
            "vs": 19997,
            "vs_text": "> 10 km",
            "time_index": "23-24",
            "analysis_date": "2026-06-24T00:00:00",
            "image": "https://api-apps.bmkg.go.id/storage/icon/cuaca/cerah-am.svg",
            "utc_datetime": "2026-06-25 00:00:00",
            "local_datetime": "2026-06-25 07:00:00"
          },
          {
            "datetime": "2026-06-25T03:00:00Z",
            "t": 29,
            "tcc": 10,
            "tp": 0.1,
            "weather": 1,
            "weather_desc": "Cerah",
            "weather_desc_en": "Sunny",
            "wd_deg": 123,
            "wd": "E",
            "wd_to": "W",
            "ws": 15.3,
            "hu": 60,
            "vs": 20005,
            "vs_text": "> 10 km",
            "time_index": "26-27",
            "analysis_date": "2026-06-24T00:00:00",
            "image": "https://api-apps.bmkg.go.id/storage/icon/cuaca/cerah-am.svg",
            "utc_datetime": "2026-06-25 03:00:00",
            "local_datetime": "2026-06-25 10:00:00"
          },
          {
            "datetime": "2026-06-25T06:00:00Z",
            "t": 28,
            "tcc": 26,
            "tp": 0,
            "weather": 1,
            "weather_desc": "Cerah",
            "weather_desc_en": "Sunny",
            "wd_deg": 133,
            "wd": "E",
            "wd_to": "W",
            "ws": 23.3,
            "hu": 68,
            "vs": 19046,
            "vs_text": "> 10 km",
            "time_index": "29-30",
            "analysis_date": "2026-06-24T00:00:00",
            "image": "https://api-apps.bmkg.go.id/storage/icon/cuaca/cerah-am.svg",
            "utc_datetime": "2026-06-25 06:00:00",
            "local_datetime": "2026-06-25 13:00:00"
          },
          {
            "datetime": "2026-06-25T09:00:00Z",
            "t": 25,
            "tcc": 14,
            "tp": 0,
            "weather": 1,
            "weather_desc": "Cerah",
            "weather_desc_en": "Sunny",
            "wd_deg": 121,
            "wd": "E",
            "wd_to": "W",
            "ws": 15.4,
            "hu": 83,
            "vs": 19995,
            "vs_text": "> 10 km",
            "time_index": "32-33",
            "analysis_date": "2026-06-24T00:00:00",
            "image": "https://api-apps.bmkg.go.id/storage/icon/cuaca/cerah-am.svg",
            "utc_datetime": "2026-06-25 09:00:00",
            "local_datetime": "2026-06-25 16:00:00"
          },
          {
            "datetime": "2026-06-25T12:00:00Z",
            "t": 23,
            "tcc": 12,
            "tp": 0,
            "weather": 1,
            "weather_desc": "Cerah",
            "weather_desc_en": "Sunny",
            "wd_deg": 115,
            "wd": "E",
            "wd_to": "W",
            "ws": 13.1,
            "hu": 95,
            "vs": 20000,
            "vs_text": "> 10 km",
            "time_index": "35-36",
            "analysis_date": "2026-06-24T00:00:00",
            "image": "https://api-apps.bmkg.go.id/storage/icon/cuaca/cerah-pm.svg",
            "utc_datetime": "2026-06-25 12:00:00",
            "local_datetime": "2026-06-25 19:00:00"
          },
          {
            "datetime": "2026-06-25T15:00:00Z",
            "t": 23,
            "tcc": 58,
            "tp": 0,
            "weather": 1,
            "weather_desc": "Cerah",
            "weather_desc_en": "Sunny",
            "wd_deg": 117,
            "wd": "E",
            "wd_to": "W",
            "ws": 13.5,
            "hu": 95,
            "vs": 20000,
            "vs_text": "> 10 km",
            "time_index": "38-39",
            "analysis_date": "2026-06-24T00:00:00",
            "image": "https://api-apps.bmkg.go.id/storage/icon/cuaca/cerah-pm.svg",
            "utc_datetime": "2026-06-25 15:00:00",
            "local_datetime": "2026-06-25 22:00:00"
          }
        ],
        [
          {
            "datetime": "2026-06-25T18:00:00Z",
            "t": 22,
            "tcc": 52,
            "tp": 0,
            "weather": 1,
            "weather_desc": "Cerah",
            "weather_desc_en": "Sunny",
            "wd_deg": 114,
            "wd": "E",
            "wd_to": "W",
            "ws": 12.7,
            "hu": 96,
            "vs": 14049,
            "vs_text": "> 10 km",
            "time_index": "41-42",
            "analysis_date": "2026-06-24T00:00:00",
            "image": "https://api-apps.bmkg.go.id/storage/icon/cuaca/cerah-pm.svg",
            "utc_datetime": "2026-06-25 18:00:00",
            "local_datetime": "2026-06-26 01:00:00"
          },
          {
            "datetime": "2026-06-25T21:00:00Z",
            "t": 22,
            "tcc": 41,
            "tp": 0,
            "weather": 1,
            "weather_desc": "Cerah",
            "weather_desc_en": "Sunny",
            "wd_deg": 116,
            "wd": "E",
            "wd_to": "W",
            "ws": 13.1,
            "hu": 95,
            "vs": 13989,
            "vs_text": "> 10 km",
            "time_index": "44-45",
            "analysis_date": "2026-06-24T00:00:00",
            "image": "https://api-apps.bmkg.go.id/storage/icon/cuaca/cerah-pm.svg",
            "utc_datetime": "2026-06-25 21:00:00",
            "local_datetime": "2026-06-26 04:00:00"
          },
          {
            "datetime": "2026-06-26T00:00:00Z",
            "t": 25,
            "tcc": 12,
            "tp": 0.2,
            "weather": 1,
            "weather_desc": "Cerah",
            "weather_desc_en": "Sunny",
            "wd_deg": 114,
            "wd": "E",
            "wd_to": "W",
            "ws": 12.9,
            "hu": 80,
            "vs": 20001,
            "vs_text": "> 10 km",
            "time_index": "47-48",
            "analysis_date": "2026-06-24T00:00:00",
            "image": "https://api-apps.bmkg.go.id/storage/icon/cuaca/cerah-am.svg",
            "utc_datetime": "2026-06-26 00:00:00",
            "local_datetime": "2026-06-26 07:00:00"
          },
          {
            "datetime": "2026-06-26T03:00:00Z",
            "t": 28,
            "tcc": 31,
            "tp": 0.2,
            "weather": 1,
            "weather_desc": "Cerah",
            "weather_desc_en": "Sunny",
            "wd_deg": 123,
            "wd": "E",
            "wd_to": "W",
            "ws": 18,
            "hu": 67,
            "vs": 11859,
            "vs_text": "> 10 km",
            "time_index": "50-51",
            "analysis_date": "2026-06-24T00:00:00",
            "image": "https://api-apps.bmkg.go.id/storage/icon/cuaca/cerah-am.svg",
            "utc_datetime": "2026-06-26 03:00:00",
            "local_datetime": "2026-06-26 10:00:00"
          },
          {
            "datetime": "2026-06-26T06:00:00Z",
            "t": 27,
            "tcc": 60,
            "tp": 0.2,
            "weather": 2,
            "weather_desc": "Cerah Berawan",
            "weather_desc_en": "Partly Cloudy",
            "wd_deg": 123,
            "wd": "E",
            "wd_to": "W",
            "ws": 18,
            "hu": 76,
            "vs": 11859,
            "vs_text": "> 10 km",
            "time_index": "53-54",
            "analysis_date": "2026-06-24T00:00:00",
            "image": "https://api-apps.bmkg.go.id/storage/icon/cuaca/cerah berawan-am.svg",
            "utc_datetime": "2026-06-26 06:00:00",
            "local_datetime": "2026-06-26 13:00:00"
          },
          {
            "datetime": "2026-06-26T09:00:00Z",
            "t": 24,
            "tcc": 64,
            "tp": 0.2,
            "weather": 2,
            "weather_desc": "Cerah Berawan",
            "weather_desc_en": "Partly Cloudy",
            "wd_deg": 121,
            "wd": "E",
            "wd_to": "W",
            "ws": 14.2,
            "hu": 87,
            "vs": 14762,
            "vs_text": "> 10 km",
            "time_index": "56-57",
            "analysis_date": "2026-06-24T00:00:00",
            "image": "https://api-apps.bmkg.go.id/storage/icon/cuaca/cerah berawan-am.svg",
            "utc_datetime": "2026-06-26 09:00:00",
            "local_datetime": "2026-06-26 16:00:00"
          },
          {
            "datetime": "2026-06-26T12:00:00Z",
            "t": 23,
            "tcc": 55,
            "tp": 0,
            "weather": 1,
            "weather_desc": "Cerah",
            "weather_desc_en": "Sunny",
            "wd_deg": 121,
            "wd": "E",
            "wd_to": "W",
            "ws": 14.2,
            "hu": 94,
            "vs": 14762,
            "vs_text": "> 10 km",
            "time_index": "59-60",
            "analysis_date": "2026-06-24T00:00:00",
            "image": "https://api-apps.bmkg.go.id/storage/icon/cuaca/cerah-pm.svg",
            "utc_datetime": "2026-06-26 12:00:00",
            "local_datetime": "2026-06-26 19:00:00"
          },
          {
            "datetime": "2026-06-26T15:00:00Z",
            "t": 23,
            "tcc": 76,
            "tp": 0,
            "weather": 2,
            "weather_desc": "Cerah Berawan",
            "weather_desc_en": "Partly Cloudy",
            "wd_deg": 112,
            "wd": "E",
            "wd_to": "W",
            "ws": 13.5,
            "hu": 94,
            "vs": 14696,
            "vs_text": "> 10 km",
            "time_index": "62-63",
            "analysis_date": "2026-06-24T00:00:00",
            "image": "https://api-apps.bmkg.go.id/storage/icon/cuaca/cerah berawan-pm.svg",
            "utc_datetime": "2026-06-26 15:00:00",
            "local_datetime": "2026-06-26 22:00:00"
          }
        ]
      ]
    }
  ]
}